reqx.py
reqx-2.0.0.dist-info/METADATA
reqx-2.0.0.dist-info/WHEEL
reqx-2.0.0.dist-info/top_level.txt
reqx-2.0.0.dist-info/RECORD
