Metadata-Version: 2.4
Name: reqx
Version: 2.0.0
Summary: Bypass cookies and user agent protection
Author: VIRUS
Requires-Python: >=3.6
Requires-Dist: requests
Requires-Dist: pycryptodome
Dynamic: author
Dynamic: requires-dist
Dynamic: requires-python
Dynamic: summary
